tsi2csv/__init__.py
tsi2csv/main.py
tsi2csv-0.0.2.dist-info/LICENSE
tsi2csv-0.0.2.dist-info/METADATA
tsi2csv-0.0.2.dist-info/WHEEL
tsi2csv-0.0.2.dist-info/entry_points.txt
tsi2csv-0.0.2.dist-info/top_level.txt
tsi2csv-0.0.2.dist-info/RECORD
