Metadata-Version: 2.1
Name: tsi2csv
Version: 0.0.2
Summary: Convert from LinkedOmics multi-omics tsi data format to csv
Home-page: https://gitlab.com/carback1/tsi2csv
Author: Richard T. Carback III
Author-email: rick.carback@gmail.com
License: UNKNOWN
Platform: UNKNOWN
Classifier: Programming Language :: Python :: 3
Classifier: License :: OSI Approved :: MIT License
Classifier: Operating System :: OS Independent
Requires-Python: >=3.6
Requires-Dist: click
